{
	"credit": "Made with Blockbench",
	"elements": [
		{
			"from": [1, 2, 14],
			"to": [14.5, 13.5, 14.5],
			"color": 7,
			"faces": {
				"north": {"uv": [0, 0, 0.5, 0.5], "texture": "#missing"},
				"east": {"uv": [0, 0, 0.5, 0.5], "texture": "#missing"},
				"south": {"uv": [0, 0, 0.5, 0.5], "texture": "#missing"},
				"west": {"uv": [0, 0, 0.5, 0.5], "texture": "#missing"},
				"up": {"uv": [0, 0, 0.5, 0.5], "texture": "#missing"},
				"down": {"uv": [0, 0, 0.5, 0.5], "texture": "#missing"}
			}
		},
		{
			"from": [0, 0, 0],
			"to": [16, 2, 16],
			"color": 3,
			"faces": {
				"north": {"uv": [0, 0, 16, 2], "texture": "#missing"},
				"east": {"uv": [0, 0, 16, 2], "texture": "#missing"},
				"south": {"uv": [0, 0, 16, 2], "texture": "#missing"},
				"west": {"uv": [0, 0, 16, 2], "texture": "#missing"},
				"up": {"uv": [0, 0, 16, 16], "texture": "#missing"},
				"down": {"uv": [0, 0, 16, 16], "texture": "#missing"}
			}
		},
		{
			"from": [1, 2, 5.5],
			"to": [14.5, 13.5, 6],
			"color": 7,
			"faces": {
				"north": {"uv": [0, 0, 0.5, 0.5], "texture": "#missing"},
				"east": {"uv": [0, 0, 0.5, 0.5], "texture": "#missing"},
				"south": {"uv": [0, 0, 0.5, 0.5], "texture": "#missing"},
				"west": {"uv": [0, 0, 0.5, 0.5], "texture": "#missing"},
				"up": {"uv": [0, 0, 0.5, 0.5], "texture": "#missing"},
				"down": {"uv": [0, 0, 0.5, 0.5], "texture": "#missing"}
			}
		},
		{
			"from": [1, 2, 5.5],
			"to": [1.5, 13.5, 14.5],
			"color": 7,
			"faces": {
				"north": {"uv": [0, 0, 0.5, 0.5], "texture": "#missing"},
				"east": {"uv": [0, 0, 0.5, 0.5], "texture": "#missing"},
				"south": {"uv": [0, 0, 0.5, 0.5], "texture": "#missing"},
				"west": {"uv": [0, 0, 0.5, 0.5], "texture": "#missing"},
				"up": {"uv": [0, 0, 0.5, 0.5], "rotation": 270, "texture": "#missing"},
				"down": {"uv": [0, 0, 0.5, 0.5], "rotation": 90, "texture": "#missing"}
			}
		},
		{
			"from": [14.5, 2, 5.5],
			"to": [15, 13.5, 14.5],
			"color": 7,
			"faces": {
				"north": {"uv": [0, 0, 0.5, 0.5], "texture": "#missing"},
				"east": {"uv": [0, 0, 0.5, 0.5], "texture": "#missing"},
				"south": {"uv": [0, 0, 0.5, 0.5], "texture": "#missing"},
				"west": {"uv": [0, 0, 0.5, 0.5], "texture": "#missing"},
				"up": {"uv": [0, 0, 0.5, 0.5], "rotation": 270, "texture": "#missing"},
				"down": {"uv": [0, 0, 0.5, 0.5], "rotation": 90, "texture": "#missing"}
			}
		},
		{
			"from": [1, 13.5, 5.5],
			"to": [15, 14, 14.5],
			"color": 7,
			"faces": {
				"north": {"uv": [0, 0, 0.5, 0.5], "rotation": 90, "texture": "#missing"},
				"east": {"uv": [0, 0, 0.5, 0.5], "texture": "#missing"},
				"south": {"uv": [0, 0, 0.5, 0.5], "rotation": 270, "texture": "#missing"},
				"west": {"uv": [0, 0, 0.5, 0.5], "texture": "#missing"},
				"up": {"uv": [0, 0, 0.5, 0.5], "rotation": 270, "texture": "#missing"},
				"down": {"uv": [0, 0, 0.5, 0.5], "rotation": 270, "texture": "#missing"}
			}
		}
	]
}